meny/__init__.py
meny/casehandlers.py
meny/cli.py
meny/config.py
meny/curses_interface.py
meny/decorators.py
meny/exceptions.py
meny/funcmap.py
meny/infos.py
meny/menu.py
meny/menylogger.py
meny/simple_interface.py
meny/strings.py
meny/utils.py
meny-1.1.1.dist-info/LICENSE
meny-1.1.1.dist-info/METADATA
meny-1.1.1.dist-info/WHEEL
meny-1.1.1.dist-info/entry_points.txt
meny-1.1.1.dist-info/top_level.txt
meny-1.1.1.dist-info/RECORD
