Metadata-Version: 2.1
Name: meny
Version: 1.1.1
Summary: Simple and sexy console interface
Home-page: https://github.com/Napam/meny
Author: Naphat Amundsen
Author-email: naphat@live.com
Classifier: Programming Language :: Python :: 3
Classifier: License :: OSI Approved :: MIT License
Classifier: Operating System :: OS Independent
Requires-Python: >=3.7
License-File: LICENSE
